setup.py
code_reviews/__init__.py
code_reviews/code_reviews.py
code_reviews.egg-info/PKG-INFO
code_reviews.egg-info/SOURCES.txt
code_reviews.egg-info/dependency_links.txt
code_reviews.egg-info/entry_points.txt
code_reviews.egg-info/requires.txt
code_reviews.egg-info/top_level.txt