Metadata-Version: 1.0
Name: code-reviews
Version: 0.0.1
Summary: code reviews and pull request monitor for github.com
Home-page: https://bitbucket.org/submax82/code_reviews/src/master/
Author: massimo
Author-email: massimo.cavalleri@gmail.com
License: GPL
Platform: UNKNOWN
